antsy.py
antsy-0.1.0.dist-info/top_level.txt
antsy-0.1.0.dist-info/RECORD
antsy-0.1.0.dist-info/WHEEL
antsy-0.1.0.dist-info/metadata.json
antsy-0.1.0.dist-info/METADATA
antsy-0.1.0.dist-info/DESCRIPTION.rst
