Metadata-Version: 2.0
Name: antsy
Version: 0.1.0
Summary: Sweet interpolated ANSI strings
Home-page: https://github.com/willyg302/antsy
Author: William Gaul
Author-email: willyg302@gmail.com
License: MIT
Platform: UNKNOWN
Classifier: License :: OSI Approved :: MIT License
Classifier: Programming Language :: Python :: 2.7
Classifier: Programming Language :: Python :: 3.4
